plf/__init__.py
plf/_pipeline.py
plf/_transfer_utils.py
plf/_version.py
plf/context.py
plf/danger.py
plf/experiment.py
plf/lab.py
plf/utils.py
pylabflow-0.3.0.3.dist-info/licenses/LICENSE
pylabflow-0.3.0.3.dist-info/METADATA
pylabflow-0.3.0.3.dist-info/WHEEL
pylabflow-0.3.0.3.dist-info/top_level.txt
pylabflow-0.3.0.3.dist-info/RECORD
