Metadata-Version: 2.4
Name: PyLabFlow
Version: 0.3.0.3
Summary: PyLabFlow is a lightweight framework that simplifies experiment management, reducing setup time with reusable components for training, logging, and checkpointing. It streamlines workflows, making it ideal for fast and efficient experimentation.
Home-page: https://github.com/ExperQuick/PyLabFlow
Author: BBEK-Anand
Author-email: 
License: Apache-2.0
Classifier: Programming Language :: Python :: 3
Classifier: License :: OSI Approved :: Apache Software License
Classifier: Operating System :: OS Independent
Requires-Python: >=3.7
License-File: LICENSE
Requires-Dist: pandas
Dynamic: author
Dynamic: classifier
Dynamic: description
Dynamic: description-content-type
Dynamic: home-page
Dynamic: license
Dynamic: license-file
Dynamic: requires-dist
Dynamic: requires-python
Dynamic: summary
